README.md
setup.py
ezSCUP/__init__.py
ezSCUP/exceptions.py
ezSCUP/files.py
ezSCUP/generators.py
ezSCUP/geometry.py
ezSCUP/handlers.py
ezSCUP/perovskite.py
ezSCUP/polarization.py
ezSCUP/projection.py
ezSCUP/settings.py
ezSCUP/simulations.py
ezSCUP.egg-info/PKG-INFO
ezSCUP.egg-info/SOURCES.txt
ezSCUP.egg-info/dependency_links.txt
ezSCUP.egg-info/not-zip-safe
ezSCUP.egg-info/requires.txt
ezSCUP.egg-info/top_level.txt