Metadata-Version: 1.2
Name: ezSCUP
Version: 2.0
Summary: SCALE-UP Python Wrapper
Home-page: https://github.com/rcote98/ezSCUP
Author: Raúl Coterillo
Author-email: raulcote98@gmail.com
License: UNKNOWN
Download-URL: https://github.com/rcote98/ezSCUP/archive/v2.0.tar.gz
Platform: UNKNOWN
Classifier: Programming Language :: Python :: 3
Classifier: License :: OSI Approved :: GNU General Public License v3 (GPLv3)
Classifier: Operating System :: OS Independent
Requires-Python: >=3.6
